azure/mgmt/networkcloud/__init__.py
azure/mgmt/networkcloud/_configuration.py
azure/mgmt/networkcloud/_network_cloud_mgmt_client.py
azure/mgmt/networkcloud/_patch.py
azure/mgmt/networkcloud/_version.py
azure/mgmt/networkcloud/py.typed
azure/mgmt/networkcloud/_utils/__init__.py
azure/mgmt/networkcloud/_utils/serialization.py
azure/mgmt/networkcloud/aio/__init__.py
azure/mgmt/networkcloud/aio/_configuration.py
azure/mgmt/networkcloud/aio/_network_cloud_mgmt_client.py
azure/mgmt/networkcloud/aio/_patch.py
azure/mgmt/networkcloud/aio/operations/__init__.py
azure/mgmt/networkcloud/aio/operations/_agent_pools_operations.py
azure/mgmt/networkcloud/aio/operations/_bare_metal_machine_key_sets_operations.py
azure/mgmt/networkcloud/aio/operations/_bare_metal_machines_operations.py
azure/mgmt/networkcloud/aio/operations/_bmc_key_sets_operations.py
azure/mgmt/networkcloud/aio/operations/_cloud_services_networks_operations.py
azure/mgmt/networkcloud/aio/operations/_cluster_managers_operations.py
azure/mgmt/networkcloud/aio/operations/_clusters_operations.py
azure/mgmt/networkcloud/aio/operations/_consoles_operations.py
azure/mgmt/networkcloud/aio/operations/_kubernetes_cluster_features_operations.py
azure/mgmt/networkcloud/aio/operations/_kubernetes_clusters_operations.py
azure/mgmt/networkcloud/aio/operations/_l2_networks_operations.py
azure/mgmt/networkcloud/aio/operations/_l3_networks_operations.py
azure/mgmt/networkcloud/aio/operations/_metrics_configurations_operations.py
azure/mgmt/networkcloud/aio/operations/_operations.py
azure/mgmt/networkcloud/aio/operations/_patch.py
azure/mgmt/networkcloud/aio/operations/_rack_skus_operations.py
azure/mgmt/networkcloud/aio/operations/_racks_operations.py
azure/mgmt/networkcloud/aio/operations/_storage_appliances_operations.py
azure/mgmt/networkcloud/aio/operations/_trunked_networks_operations.py
azure/mgmt/networkcloud/aio/operations/_virtual_machines_operations.py
azure/mgmt/networkcloud/aio/operations/_volumes_operations.py
azure_mgmt_networkcloud-2.2.0.dist-info/licenses/LICENSE
azure_mgmt_networkcloud-2.2.0.dist-info/METADATA
azure_mgmt_networkcloud-2.2.0.dist-info/WHEEL
azure_mgmt_networkcloud-2.2.0.dist-info/top_level.txt
azure_mgmt_networkcloud-2.2.0.dist-info/RECORD
